fa_api
