Metadata-Version: 2.1
Name: fa-api
Version: 0.2
Summary: API wrapper for ruz.fa.ru
Home-page: https://github.com/GeorgiyDemo/fa_api
Author: Georgiy Demenchuk
Author-email: demenchuk.george@protonmail.com
License: GPLv3
Keywords: python api wrapper ruz fa ru faru library апи питон пайтон обёртка библиотека
Platform: UNKNOWN
